{"cameraMode":{"drawMode":0,"name":"Shaded","section":"Shading Mode"},"sceneLighting":true,"audioPlay":false,"sceneViewState":{"m_AlwaysRefresh":false,"showFog":true,"showSkybox":true,"showFlares":true,"showImageEffects":true,"showParticleSystems":true,"showVisualEffectGraphs":true,"m_FxEnabled":true},"in2DMode":false,"pivot":{"x":-61.47235107421875,"y":-41.32769775390625,"z":812.916015625},"rotation":{"x":0.3226906359195709,"y":0.3061932623386383,"z":-0.11122135072946549,"w":0.888714611530304},"size":825.7064208984375,"orthographic":false}